LICENSE
fastapi_slackeventsapi/__init__.py
fastapi_slackeventsapi/event_dispatcher.py
fastapi_slackeventsapi/event_manager.py
fastapi_slackeventsapi-0.1.0.dist-info/LICENSE
fastapi_slackeventsapi-0.1.0.dist-info/WHEEL
fastapi_slackeventsapi-0.1.0.dist-info/METADATA
fastapi_slackeventsapi-0.1.0.dist-info/RECORD
