Metadata-Version: 2.1
Name: fastapi-slackeventsapi
Version: 0.1.0
Summary: FastAPI Implementation of slackeventsapi
Home-page: https://github.com/und3v3l0p3d/fastapi_slackeventsapi
License: MIT
Keywords: fastapi,slack,slackeventsapi
Author: Phygitalism
Requires-Python: >=3.7,<4
Classifier: Framework :: AsyncIO
Classifier: Intended Audience :: Developers
Classifier: License :: OSI Approved :: MIT License
Classifier: Programming Language :: Python :: 3
Classifier: Programming Language :: Python :: 3 :: Only
Classifier: Programming Language :: Python :: 3.6
Classifier: Programming Language :: Python :: 3.7
Classifier: Programming Language :: Python :: 3.8
Classifier: Programming Language :: Python :: 3.9
Classifier: Topic :: Communications :: Chat
Classifier: Topic :: Office/Business
Classifier: Topic :: System :: Networking
Requires-Dist: aiojobs (>=0.3.0,<0.4.0)
Requires-Dist: async-timeout (>=3.0.1,<4.0.0)
Requires-Dist: fastapi (>=0.63.0,<0.64.0)
Project-URL: Repository, https://github.com/und3v3l0p3d/fastapi_slackeventsapi
